nonebot_plugin_dailysign-0.1.0.1.dist-info/METADATA
nonebot_plugin_dailysign-0.1.0.1.dist-info/WHEEL
nonebot_plugin_dailysign-0.1.0.1.dist-info/licenses/LICENSE
nonebot_plugin_dailysign/__init__.py
nonebot_plugin_dailysign/config.py
nonebot_plugin_dailysign/data_model.py
nonebot_plugin_dailysign/data_source.py
nonebot_plugin_dailysign/models.py
nonebot_plugin_dailysign-0.1.0.1.dist-info/RECORD
