Metadata-Version: 2.1
Name: nonebot-plugin-dailysign
Version: 0.1.0.1
Summary: 一个简单的每日签到插件
Home-page: https://github.com/kexue-z/nonebot-plugin-dailysign
Author-Email: kexue <xana278@foxmail.com>, kexue <x@kexue.io>
License: MIT License
Project-URL: Homepage, https://github.com/kexue-z/nonebot-plugin-dailysign
Requires-Python: <4.0,>=3.8
Requires-Dist: nonebot2[fastapi]>=2.0.0
Requires-Dist: nonebot-adapter-onebot>=2.0.0
Requires-Dist: nonebot-plugin-tortoise-orm>=0.1.0
